Metadata-Version: 2.1
Name: num-systems
Version: 1.1
Summary: Functions to deal with uncomfortable numeric systems
Author-email: mihamar2005@gmail.com
